[{"date":"2017-11-27","symbol":"AEON","name":"AEON","quantity":12.4,"price":3.04,"position":37.696000000000005,"btcPosition":0.0039053056000000006},{"date":"2017-11-27","symbol":"BCN","name":"ByteCoin","quantity":8500,"price":0.001709,"position":14.5265,"btcPosition":0.0015049454},{"date":"2017-11-27","symbol":"BTC","name":"Bitcoin","quantity":0.00248323,"price":9654.41,"position":23.9741205443,"btcPosition":0.00248371888838948},{"date":"2017-11-27","symbol":"BNT","name":"Bancor Network","quantity":3.42,"price":2.67,"position":9.1314,"btcPosition":0.0009460130399999999},{"date":"2017-11-27","symbol":"DASH","name":"Dash","quantity":0.035,"price":627,"position":21.945000000000004,"btcPosition":0.002273502},{"date":"2017-11-27","symbol":"DCT","name":"Decent","quantity":8.221,"price":0.9505,"position":7.8140605,"btcPosition":0.0008095366678},{"date":"2017-11-27","symbol":"DNT","name":"District0x Network","quantity":47.75,"price":0.04634,"position":2.212735,"btcPosition":0.00022923934599999998},{"date":"2017-11-27","symbol":"DOGE","name":"DogeCoin","quantity":6000,"price":0.001954,"position":11.724,"btcPosition":0.0012146064},{"date":"2017-11-27","symbol":"EDG","name":"EDG","quantity":11,"price":0.9058,"position":9.9638,"btcPosition":0.0010322496800000002},{"date":"2017-11-27","symbol":"EOS","name":"EOS","quantity":7.524,"price":2.8,"position":21.0672,"btcPosition":0.0021825619199999998},{"date":"2017-11-27","symbol":"ETC","name":"Ethereum Classic","quantity":0.701,"price":25.29,"position":17.728289999999998,"btcPosition":0.0018366508439999997},{"date":"2017-11-27","symbol":"ETH","name":"Ethereum","quantity":0.029,"price":475.78,"position":13.79762,"btcPosition":0.001429433432},{"date":"2017-11-27","symbol":"LSK","name":"Lisk","quantity":3.31,"price":7.75,"position":25.6525,"btcPosition":0.002657599},{"date":"2017-11-27","symbol":"LTC","name":"LiteCoin","quantity":0.2,"price":90.13,"position":18.026,"btcPosition":0.0018674936},{"date":"2017-11-27","symbol":"MAID","name":"MaidSafeCoin","quantity":20,"price":0.4927,"position":9.854000000000001,"btcPosition":0.0010208744},{"date":"2017-11-27","symbol":"NXT","name":"Nxt","quantity":94,"price":0.211,"position":19.834,"btcPosition":0.0020548024},{"date":"2017-11-27","symbol":"OAX","name":"OpenANX","quantity":5.587,"price":0.4191,"position":2.3415117,"btcPosition":0.00024258061211999998},{"date":"2017-11-27","symbol":"PLBT","name":"Polybius","quantity":1.346,"price":4.04,"position":5.4378400000000005,"btcPosition":0.000563360224},{"date":"2017-11-27","symbol":"PPC","name":"PeerCoin","quantity":5.618,"price":2.21,"position":12.41578,"btcPosition":0.001286274808},{"date":"2017-11-27","symbol":"QAU","name":"Quantum","quantity":59.229,"price":0.117,"position":6.929793,"btcPosition":0.0007179265548},{"date":"2017-11-27","symbol":"SC","name":"SiaCoin","quantity":1400,"price":0.006372,"position":8.9208,"btcPosition":0.00092419488},{"date":"2017-11-27","symbol":"SNC","name":"SunContract","quantity":112.863,"price":0.1043,"position":11.7716109,"btcPosition":0.00121953888924},{"date":"2017-11-27","symbol":"STRAT","name":"Stratis","quantity":1.844,"price":5.41,"position":9.976040000000001,"btcPosition":0.0010335177440000001},{"date":"2017-11-27","symbol":"STX","name":"Stox","quantity":4.167,"price":0.5777,"position":2.4072758999999997,"btcPosition":0.00024939378324},{"date":"2017-11-27","symbol":"XDN","name":"DigitalNote","quantity":3700,"price":0.002453,"position":9.0761,"btcPosition":0.00094028396},{"date":"2017-11-27","symbol":"XEM","name":"NEM","quantity":38,"price":0.2194,"position":8.337200000000001,"btcPosition":0.0008637339200000001},{"date":"2017-11-27","symbol":"XMR","name":"Monero","quantity":0.12,"price":165.84,"position":19.9008,"btcPosition":0.00206172288},{"date":"2017-11-27","symbol":"XRP","name":"Ripple","quantity":62,"price":0.2467,"position":15.2954,"btcPosition":0.00158460344},{"date":"2017-11-27","symbol":"ZEC","name":"ZCash","quantity":0.04,"price":339.2,"position":13.568,"btcPosition":0.0014056448},{"date":"2017-11-27","symbol":"ZRC","name":"ZR Coin","quantity":7.808,"price":1.69,"position":13.19552,"btcPosition":0.001367055872},{"date":"2017-11-27","symbol":"ZRX","name":"0x Protocol","quantity":28.066,"price":0.2298,"position":6.4495667999999995,"btcPosition":0.0006681751204799999}]